setup.py
distributions/Binomialdistribution.py
distributions/Gaussiandistribution.py
distributions/Generaldistribution.py
distributions/__init__.py
dkaqn119_distributions.egg-info/PKG-INFO
dkaqn119_distributions.egg-info/SOURCES.txt
dkaqn119_distributions.egg-info/dependency_links.txt
dkaqn119_distributions.egg-info/not-zip-safe
dkaqn119_distributions.egg-info/top_level.txt